<?xml version="1.0" encoding="utf-8" ?>
<dwsync>
<file name="en_dlg.js" server="C:/xampp/htdocs/cabletica/" local="129111544000000000" remote="129111544000000000" />
<file name="es_dlg.js" server="C:/xampp/htdocs/cabletica/" local="129111544000000000" remote="129111544000000000" />
<file name="en_dlg.js" server="C:/xampp/htdocs/mabodesigns/" local="129111544000000000" remote="129111544000000000" />
<file name="es_dlg.js" server="C:/xampp/htdocs/mabodesigns/" local="129111544000000000" remote="129111544000000000" />
<file name="en_dlg.js" server="C:/xampp/htdocs/mabo/" local="129111544000000000" remote="129111544000000000" />
<file name="es_dlg.js" server="C:/xampp/htdocs/mabo/" local="129111544000000000" remote="129111544000000000" />
<file name="en_dlg.js" server="C:/xampp/htdocs/ilmagentasalon/" local="129111544000000000" remote="129111544000000000" />
<file name="es_dlg.js" server="C:/xampp/htdocs/ilmagentasalon/" local="129111544000000000" remote="129111544000000000" />
</dwsync>