<?xml version="1.0" encoding="utf-8" ?>
<dwsync>
<file name="buttons.png" server="C:/xampp/htdocs/cabletica/" local="129111545460000000" remote="129111545460000000" />
<file name="items.gif" server="C:/xampp/htdocs/cabletica/" local="129111545460000000" remote="129111545460000000" />
<file name="menu_arrow.gif" server="C:/xampp/htdocs/cabletica/" local="129111545460000000" remote="129111545460000000" />
<file name="menu_check.gif" server="C:/xampp/htdocs/cabletica/" local="129111545440000000" remote="129111545440000000" />
<file name="progress.gif" server="C:/xampp/htdocs/cabletica/" local="129111545440000000" remote="129111545440000000" />
<file name="tabs.gif" server="C:/xampp/htdocs/cabletica/" local="129111545440000000" remote="129111545440000000" />
<file name="buttons.png" server="C:/xampp/htdocs/mabodesigns/" local="129111545460000000" remote="129111545460000000" />
<file name="items.gif" server="C:/xampp/htdocs/mabodesigns/" local="129111545460000000" remote="129111545460000000" />
<file name="menu_arrow.gif" server="C:/xampp/htdocs/mabodesigns/" local="129111545460000000" remote="129111545460000000" />
<file name="menu_check.gif" server="C:/xampp/htdocs/mabodesigns/" local="129111545440000000" remote="129111545440000000" />
<file name="progress.gif" server="C:/xampp/htdocs/mabodesigns/" local="129111545440000000" remote="129111545440000000" />
<file name="tabs.gif" server="C:/xampp/htdocs/mabodesigns/" local="129111545440000000" remote="129111545440000000" />
<file name="buttons.png" server="C:/xampp/htdocs/mabo/" local="129111545460000000" remote="129111545460000000" />
<file name="items.gif" server="C:/xampp/htdocs/mabo/" local="129111545460000000" remote="129111545460000000" />
<file name="menu_arrow.gif" server="C:/xampp/htdocs/mabo/" local="129111545460000000" remote="129111545460000000" />
<file name="menu_check.gif" server="C:/xampp/htdocs/mabo/" local="129111545440000000" remote="129111545440000000" />
<file name="progress.gif" server="C:/xampp/htdocs/mabo/" local="129111545440000000" remote="129111545440000000" />
<file name="tabs.gif" server="C:/xampp/htdocs/mabo/" local="129111545440000000" remote="129111545440000000" />
<file name="buttons.png" server="C:/xampp/htdocs/ilmagentasalon/" local="129111545460000000" remote="129111545460000000" />
<file name="items.gif" server="C:/xampp/htdocs/ilmagentasalon/" local="129111545460000000" remote="129111545460000000" />
<file name="menu_arrow.gif" server="C:/xampp/htdocs/ilmagentasalon/" local="129111545460000000" remote="129111545460000000" />
<file name="menu_check.gif" server="C:/xampp/htdocs/ilmagentasalon/" local="129111545440000000" remote="129111545440000000" />
<file name="progress.gif" server="C:/xampp/htdocs/ilmagentasalon/" local="129111545440000000" remote="129111545440000000" />
<file name="tabs.gif" server="C:/xampp/htdocs/ilmagentasalon/" local="129111545440000000" remote="129111545440000000" />
</dwsync>